mlog_extended/__init__.py
mlog_extended/__main__.py
mlog_extended/basic_compiler.py
mlog_extended/basic_decompiler.py
mlog_extended/compilation_error.py
mlog_extended/extended_compiler.py
mlog_extended/procedural_compiler.py
mlog_extended/procedural_structures.py
mlog_extended/extra_instructions/__init__.py
mlog_extended/extra_instructions/control.py
mlog_extended/extra_instructions/draw.py
mlog_extended/extra_instructions/extended_let.py
mlog_extended/extra_instructions/jump_if.py
mlog_extended/extra_instructions/kwargs_parser.py
mlog_extended/extra_instructions/radars.py
mlog_extended/extra_instructions/unit_control.py
mlog_extended/extra_instructions/unit_locate.py
mlog_extended/extra_instructions/unsafe_call_return.py
mlog_extended-0.1.5.dist-info/LICENSE
mlog_extended-0.1.5.dist-info/METADATA
mlog_extended-0.1.5.dist-info/WHEEL
mlog_extended-0.1.5.dist-info/top_level.txt
mlog_extended-0.1.5.dist-info/RECORD
