Metadata-Version: 2.1
Name: mlog-extended
Version: 0.1.5
Summary: Extended Mindustry logic and its compiler
Home-page: https://github.com/UMRnInside/MlogExtended
Author: UMRnInside
Author-email: 30196401+UMRnInside@users.noreply.github.com
License: UNKNOWN
Project-URL: Bug Tracker, https://github.com/UMRnInside/MlogExtended/issues
Platform: UNKNOWN
Classifier: Programming Language :: Python :: 3
Classifier: License :: OSI Approved :: MIT License
Classifier: Operating System :: OS Independent
Requires-Python: >=3.6
License-File: LICENSE
